{
	"138.jpg": [
		"",
		"",
		"",
		"",
		"",
		"",
		"",
		"",
		"",
		"",
		"",
		"",
		"",
		"",
		"",
		"",
		"",
		"",
		"",
		"",
		"",
		"",
		"",
		"",
		"",
		"",
		"",
		"",
		"",
		"",
		"",
		"",
		"",
		"",
		"",
		"",
		"",
		"",
		"",
		"",
		"",
		"",
		"",
		""
	],
	"182.jpg": [
		"",
		"",
		"",
		"",
		"",
		"",
		"",
		"",
		"",
		"",
		"",
		"",
		"",
		"",
		"",
		"",
		"",
		"",
		"",
		"",
		"",
		"",
		"",
		"",
		"",
		"",
		"",
		"",
		"",
		"",
		"",
		"",
		"",
		"",
		"",
		"",
		"",
		"",
		"",
		"",
		"",
		"",
		"",
		""
	],
	"19.jpg": [
		"",
		"",
		"",
		"",
		"",
		"",
		"",
		"",
		"",
		"",
		"",
		"",
		"",
		"",
		"",
		"",
		"",
		"",
		"",
		"",
		"",
		"",
		"",
		"",
		"",
		"",
		"",
		"",
		"",
		"",
		"",
		"",
		"",
		"",
		"",
		"",
		"",
		"",
		"",
		"",
		"",
		"",
		"",
		""
	],
	"113.jpg": [
		"He seems focused, but has an evil eye. ",
		"50",
		"male",
		"The skin color is white",
		"Western European",
		"on the picture are his body is not shown.",
		"he looks angry, because his eyebrows are drawn together.",
		"The man looks angry or sour through his eyes.",
		"He has a glazed ",
		"He has no hair",
		"He has no hair",
		"You can not see it on the picture",
		"You can not see it on the picture",
		"You can not see it on the picture",
		"You can not see it on the picture",
		"You can not see it on the picture",
		"The man looks sour and angry through his grim face, that you can see through the contracted eyebrows and the grim facial expression.",
		"oval",
		"a little big and snub nose",
		"thin",
		"small and closed",
		"high cheeks, well groomed ",
		"short beard, groomed beard and the color of the beard is gray",
		"bushy eyebrows, slightly closed eyes and brown eye color ",
		"You can not see his arms in the picture ",
		"You can not see his hands in the picture ",
		"You can not see his chest in the picture ",
		"You can not see his belly in the picture ",
		"You can not see his legs in the picture ",
		"You can not see his feets in the picture ",
		"He looks stocky, but you can't see his whole body on his face.",
		"He looks grim, sour and angry through his eyes.",
		"6",
		"4",
		"unfriendly",
		"untrustworthy ",
		"No it does not",
		"In the background it is gray.",
		"14",
		"male",
		"female",
		"No I think not ",
		"neutral",
		"Rather, it has a negative effect, as the person seems evil."
	],
	"159.jpg": [
		"",
		"",
		"",
		"",
		"",
		"",
		"",
		"",
		"",
		"",
		"",
		"",
		"",
		"",
		"",
		"",
		"",
		"",
		"",
		"",
		"",
		"",
		"",
		"",
		"",
		"",
		"",
		"",
		"",
		"",
		"",
		"",
		"",
		"",
		"",
		"",
		"",
		"",
		"",
		"",
		"",
		"",
		"",
		""
	]
}